research_paper_finder/__init__.py
research_paper_finder/__main__.py
research_paper_finder/finder.py
research_paper_finder/test.py
IEEE_Research_Paper_Finder-0.0.2.dist-info/METADATA
IEEE_Research_Paper_Finder-0.0.2.dist-info/WHEEL
IEEE_Research_Paper_Finder-0.0.2.dist-info/entry_points.txt
IEEE_Research_Paper_Finder-0.0.2.dist-info/top_level.txt
IEEE_Research_Paper_Finder-0.0.2.dist-info/RECORD
