Metadata-Version: 2.1
Name: IEEE-Research-Paper-Finder
Version: 0.0.2
Summary: This is a command line tool to extract research paper details along with their download links with the help of keywords .
Home-page: https://github.com/subhomoy-roy-choudhury/IEEE-Research-Paper-Finder-pip
Author: Subhomoy Roy Choudhury
Author-email: subhomoyrchoudhury@gmail.com
License: MIT
Platform: UNKNOWN
Classifier: License :: OSI Approved :: MIT License
Classifier: Programming Language :: Python :: 3
Classifier: Programming Language :: Python :: 3.7
Classifier: Programming Language :: Python :: 3.8
Requires-Dist: selenium
Requires-Dist: beautifulsoup4
Requires-Dist: chromedriver-autoinstaller
Requires-Dist: requests
